monkeypaint/__init__.py
monkeypaint/__main__.py
monkeypaint/colorapi.py
monkeypaint/py.typed
monkeypaint-1.0.2.dist-info/LICENSE.txt
monkeypaint-1.0.2.dist-info/METADATA
monkeypaint-1.0.2.dist-info/WHEEL
monkeypaint-1.0.2.dist-info/entry_points.txt
monkeypaint-1.0.2.dist-info/top_level.txt
monkeypaint-1.0.2.dist-info/RECORD
