Metadata-Version: 2.1
Name: monkeypaint
Version: 1.0.2
Summary: Generate color palettes for Kinesis Freestyle Edge keyboards
Home-page: https://github.com/brettcs/monkeypaint
Author: Brett Smith
Author-email: brettcsmith@brettcsmith.org
License: GNU Affero General Public License version 3
Project-URL: Documentation, https://github.com/brettcs/monkeypaint
Project-URL: Source, https://github.com/brettcs/monkeypaint
Classifier: Development Status :: 5 - Production/Stable
Classifier: Environment :: Console
Classifier: Intended Audience :: End Users/Desktop
Classifier: Operating System :: OS Independent
Classifier: Programming Language :: Python :: 3
Classifier: Programming Language :: Python :: 3.9
Classifier: Topic :: System :: Hardware
Classifier: Typing :: Typed
Requires-Python: >=3.9
License-File: LICENSE.txt
Requires-Dist: appdirs (>=1.4.1)
Requires-Dist: requests (>=2.20)
